{"_id":"0x01163F6894493F9ecb59c30807A1296b0E00cbBA","tokenIds":[5553],"count":1,"lastActive":"2021-12-27T08:13:55.000Z","transactionCount":1,"ensName":null,"lastUpdated":"2023-03-29T16:43:38.481Z","dateCreated":"2023-03-29T16:43:38.481Z","rank":51,"overallRank":1336,"salesReport":{"buys":{"ethValue":0.064,"averageEthValue":0.064,"events":1,"usdValue":259.5236765248,"averageUsdValue":259.5236765248},"sales":{"ethValue":0,"averageEthValue":0,"events":0,"usdValue":0,"averageUsdValue":0}},"totalTransactionPages":1}