{"_id":"0xc8fbE3BbADCd1829e153F1837Fc5F7C53F280686","tokenIds":[],"count":0,"lastActive":"2021-12-28T10:34:31.000Z","transactionCount":2,"ensName":"alxalxalx.eth","lastUpdated":"2023-03-29T16:44:40.719Z","dateCreated":"2023-03-29T16:43:58.836Z","rank":52,"overallRank":3974,"salesReport":{"buys":{"ethValue":0.1,"averageEthValue":0.1,"events":1,"usdValue":409.88161601900003,"averageUsdValue":409.88161601900003},"sales":{"ethValue":0.125,"averageEthValue":0.125,"events":1,"usdValue":468.245519285,"averageUsdValue":468.245519285}},"totalTransactionPages":1}