{"_id":"0xf5F1337e89cb951b44BE8dA7F7b36961bbb1BF10","tokenIds":[8524],"count":1,"lastActive":"2022-01-11T11:54:34.000Z","transactionCount":1,"ensName":null,"lastUpdated":"2023-03-29T16:45:00.848Z","dateCreated":"2023-03-29T16:44:40.977Z","rank":51,"overallRank":1336,"salesReport":{"buys":{"ethValue":0.059,"averageEthValue":0.059,"events":1,"usdValue":223.92081195928998,"averageUsdValue":223.92081195928998},"sales":{"ethValue":0,"averageEthValue":0,"events":0,"usdValue":0,"averageUsdValue":0}},"totalTransactionPages":1}