{"_id":"0x3A010dae01FDcf786A38e033c01C5AfE058d9b51","tokenIds":[6805,6807,8581],"count":3,"lastActive":"2022-03-11T14:04:53.000Z","transactionCount":3,"ensName":null,"lastUpdated":"2023-03-29T16:45:21.912Z","dateCreated":"2023-03-29T16:45:21.912Z","rank":49,"overallRank":439,"salesReport":{"buys":{"ethValue":0.076,"averageEthValue":0.025333333333333333,"events":3,"usdValue":200.6679345242,"averageUsdValue":66.88931150806667},"sales":{"ethValue":0,"averageEthValue":0,"events":0,"usdValue":0,"averageUsdValue":0}},"totalTransactionPages":1}