{"_id":"0x0f31b471Aa454AfCD3D5a1bF215Af65DC4A2DFC4","tokenIds":[],"count":0,"lastActive":"2022-02-06T04:54:28.000Z","transactionCount":11,"ensName":"gallowsknight.eth","lastUpdated":"2023-03-29T16:45:21.506Z","dateCreated":"2023-03-29T16:42:16.398Z","rank":52,"overallRank":3974,"salesReport":{"buys":{"ethValue":0.25599999999999995,"averageEthValue":0.04266666666666666,"events":6,"usdValue":872.98087833996,"averageUsdValue":145.49681305666},"sales":{"ethValue":0.35200000000000015,"averageEthValue":0.035200000000000016,"events":10,"usdValue":1329.0690729810008,"averageUsdValue":132.90690729810007}},"totalTransactionPages":1}