{"_id":"0xE23cdF5c95C34f140AF52Ec25D1Cd226cC94582f","tokenIds":[],"count":0,"lastActive":"2021-12-29T01:48:54.000Z","transactionCount":2,"ensName":null,"lastUpdated":"2023-03-29T16:44:40.816Z","dateCreated":"2023-03-29T16:44:19.336Z","rank":52,"overallRank":3974,"salesReport":{"buys":{"ethValue":0.049,"averageEthValue":0.049,"events":1,"usdValue":187.10228655223003,"averageUsdValue":187.10228655223003},"sales":{"ethValue":0.07,"averageEthValue":0.07,"events":1,"usdValue":262.27168282560007,"averageUsdValue":262.27168282560007}},"totalTransactionPages":1}