{"_id":"0xFeE836516a3Fc5f053F35964a2Bed9af65Da8159","tokenIds":[],"count":0,"lastActive":"2021-12-26T22:50:51.000Z","transactionCount":4,"ensName":"valin.eth","lastUpdated":"2023-03-29T16:44:18.881Z","dateCreated":"2023-03-29T16:42:57.713Z","rank":52,"overallRank":3974,"salesReport":{"buys":{"ethValue":0.035,"averageEthValue":0.0175,"events":2,"usdValue":143.4342,"averageUsdValue":71.7171},"sales":{"ethValue":0.23,"averageEthValue":0.115,"events":2,"usdValue":913.825983705,"averageUsdValue":456.9129918525}},"totalTransactionPages":1}