{"_id":"0x2C1159E6570AC6856Bcd33c65e36BcadA108A958","tokenIds":[],"count":0,"lastActive":"2021-12-27T07:24:34.000Z","transactionCount":7,"ensName":"superfluous.eth","lastUpdated":"2023-03-29T16:44:40.484Z","dateCreated":"2023-03-29T16:42:57.743Z","rank":52,"overallRank":3974,"salesReport":{"buys":{"ethValue":0.083,"averageEthValue":0.0166,"events":5,"usdValue":339.33289573376004,"averageUsdValue":67.866579146752},"sales":{"ethValue":0.47180000000000005,"averageEthValue":0.09436000000000001,"events":5,"usdValue":1891.551498457002,"averageUsdValue":378.3102996914004}},"totalTransactionPages":1}