{"_id":"0xE9012a724562B96785B09250152a601F4970503d","tokenIds":[],"count":0,"lastActive":"2021-12-29T22:33:54.000Z","transactionCount":4,"ensName":"jon123.eth","lastUpdated":"2023-03-29T16:44:40.833Z","dateCreated":"2023-03-29T16:44:19.401Z","rank":52,"overallRank":3974,"salesReport":{"buys":{"ethValue":0.195,"averageEthValue":0.0975,"events":2,"usdValue":743.5237534764001,"averageUsdValue":371.76187673820004},"sales":{"ethValue":0.178,"averageEthValue":0.089,"events":2,"usdValue":654.9288008812,"averageUsdValue":327.4644004406}},"totalTransactionPages":1}