{"_id":"0xfAb38152F75b2210C842450fEDC33EB239C2845C","tokenIds":[9825],"count":1,"lastActive":"2022-01-22T18:01:06.000Z","transactionCount":1,"ensName":null,"lastUpdated":"2023-03-29T16:45:01.102Z","dateCreated":"2023-03-29T16:45:01.102Z","rank":51,"overallRank":1336,"salesReport":{"buys":{"ethValue":0.026,"averageEthValue":0.026,"events":1,"usdValue":62.13054520426,"averageUsdValue":62.13054520426},"sales":{"ethValue":0,"averageEthValue":0,"events":0,"usdValue":0,"averageUsdValue":0}},"totalTransactionPages":1}