{"_id":"0x0579535Ebc92589e2575dce8Da7acDe401212f6a","_rev":null,"count":1,"rank":48,"overallRank":1236,"tokenIds":[6433],"latestTransactionInitiatorId":"0xb5f8d6dc02599efdd3c880143e04576ea85536cd907191b1744bded880d503da","latestTransactionId":"0xb5f8d6dc02599efdd3c880143e04576ea85536cd907191b1744bded880d503da","ensName":"derekx.eth","lastActive":"2022-03-01T18:00:31.000Z","lastUpdated":"2023-02-11T16:54:01.344Z","dateCreated":"2023-02-11T16:36:24.346Z","salesReport":{"buys":{"ethValue":0.025,"averageEthValue":0.025,"events":1,"usdValue":101.59842476725001,"averageUsdValue":101.59842476725001},"sales":{"ethValue":0,"averageEthValue":0,"events":0,"usdValue":0,"averageUsdValue":0}}}