{"_id":"0x19ad8901ad89F656F6fbf4De099Ab317dEDBC28e","_rev":null,"count":10,"rank":22,"overallRank":81,"tokenIds":[3278,3279,3280,3281,3282,3283,3284,3285,3286,3287],"latestTransactionInitiatorId":"0x30e91ad72bf962412a5ba200c92beaa245c6309f86a57021265c6dca9b942125","latestTransactionId":"0x30e91ad72bf962412a5ba200c92beaa245c6309f86a57021265c6dca9b942125","ensName":"siduck.eth","lastActive":"2021-12-26T20:58:46.000Z","lastUpdated":"2023-02-11T16:33:53.207Z","dateCreated":"2023-02-11T16:33:53.207Z","salesReport":{"buys":{"ethValue":0,"averageEthValue":0,"events":0,"usdValue":0,"averageUsdValue":0},"sales":{"ethValue":0,"averageEthValue":0,"events":0,"usdValue":0,"averageUsdValue":0}}}