{"_id":"0x271D39e1A9DB6b77aD017532920eb78fF136092C","_rev":null,"count":1,"rank":44,"overallRank":1449,"tokenIds":[4120],"latestTransactionInitiatorId":"0x0efd6eaedd865476c4ae42dda127e2865b59795494f3a7e78fe616ab08bb616c","latestTransactionId":"0xfcc832120b256b1b8659f6d97be4213b69e9aa60141447af8ecce8af0485d2a5","ensName":null,"lastActive":"2021-12-27T05:32:34.000Z","lastUpdated":"2023-02-11T16:42:23.691Z","dateCreated":"2023-02-11T16:35:18.536Z","salesReport":{"buys":{"ethValue":0.0635,"averageEthValue":0.021166666666666667,"events":3,"usdValue":260.23062,"averageUsdValue":86.74354},"sales":{"ethValue":0.16,"averageEthValue":0.08,"events":2,"usdValue":637.1214560022499,"averageUsdValue":318.56072800112497}}}