{"_id":"0x333bf566Ca4c200a1fBA586bFa6b100b28004c9d","_rev":null,"count":4,"rank":45,"overallRank":269,"tokenIds":[4029,6764,890,9064],"latestTransactionInitiatorId":"0xdce2fc74f2f0447971875d2dcb854ccc5dd2d93e56c13fb8e19bce717390f5cd","latestTransactionId":"0xdce2fc74f2f0447971875d2dcb854ccc5dd2d93e56c13fb8e19bce717390f5cd","ensName":null,"lastActive":"2022-03-11T09:58:12.000Z","lastUpdated":"2023-02-11T16:54:01.395Z","dateCreated":"2023-02-11T16:40:01.839Z","salesReport":{"buys":{"ethValue":0.5619999999999999,"averageEthValue":0.11239999999999999,"events":5,"usdValue":2300.12165467384,"averageUsdValue":460.02433093476805},"sales":{"ethValue":0,"averageEthValue":0,"events":0,"usdValue":0,"averageUsdValue":0}}}