{"_id":"0x3680c67AA6DBb40624c380dE5dfea2505fD0a102","_rev":null,"count":1,"rank":44,"overallRank":1449,"tokenIds":[9264],"latestTransactionInitiatorId":null,"latestTransactionId":"0x655e18ac056da7950996f539d827d860cea43c7fdd5c348e86c21e3a1b618877","ensName":null,"lastActive":null,"lastUpdated":"2023-02-11T16:42:23.905Z","dateCreated":"2023-02-11T16:42:23.905Z","salesReport":{"buys":{"ethValue":0,"averageEthValue":0,"events":0,"usdValue":0,"averageUsdValue":0},"sales":{"ethValue":0,"averageEthValue":0,"events":0,"usdValue":0,"averageUsdValue":0}}}