{"_id":"0x405cD320d798F8710cBB3481C1504359594e3154","_rev":null,"count":1,"rank":41,"overallRank":1484,"tokenIds":[9618],"latestTransactionInitiatorId":"0x80711fb87b5c00510444f11c99182d2ddb24392b61fd7ad0d7201a8364a433b1","latestTransactionId":"0x80711fb87b5c00510444f11c99182d2ddb24392b61fd7ad0d7201a8364a433b1","ensName":null,"lastActive":"2021-12-27T10:27:41.000Z","lastUpdated":"2023-02-11T16:37:56.135Z","dateCreated":"2023-02-11T16:37:56.135Z","salesReport":{"buys":{"ethValue":0.073,"averageEthValue":0.073,"events":1,"usdValue":296.13786705774,"averageUsdValue":296.13786705774},"sales":{"ethValue":0,"averageEthValue":0,"events":0,"usdValue":0,"averageUsdValue":0}}}