{"_id":"0x54370CBCAeEE8b3Fc8bE6f2dD1E465B5CDFaCC8F","_rev":null,"count":1,"rank":44,"overallRank":1386,"tokenIds":[],"latestTransactionInitiatorId":"0x5ef59975b52bebb81d60b54a01161bd12099585dc18b86f8732e1a2141a6cb36","latestTransactionId":"0x5ef59975b52bebb81d60b54a01161bd12099585dc18b86f8732e1a2141a6cb36","ensName":"pondtard.eth","lastActive":"2021-12-26T23:46:17.000Z","lastUpdated":"2023-02-11T16:36:24.150Z","dateCreated":"2023-02-11T16:35:18.532Z","salesReport":{"buys":{"ethValue":0.033,"averageEthValue":0.0165,"events":2,"usdValue":135.0590487648,"averageUsdValue":67.5295243824},"sales":{"ethValue":0.054,"averageEthValue":0.054,"events":1,"usdValue":220.65439955328,"averageUsdValue":220.65439955328}}}