{"_id":"0x62abF60E92D1d48669690896d9154C67e2078A38","_rev":null,"count":0,"rank":42,"overallRank":3041,"tokenIds":[],"latestTransactionInitiatorId":"0xb16e3957f8c29f92693834ce9fa51996de0e59496dd5e5b72c65689c49f7e8f8","latestTransactionId":"0x8cff18eb0861a5850d0daf825fb4a93668f8e778012f6a954cab5a77729b2ee1","ensName":null,"lastActive":"2021-12-26T22:28:03.000Z","lastUpdated":"2023-02-11T16:37:55.470Z","dateCreated":"2023-02-11T16:35:18.363Z","salesReport":{"buys":{"ethValue":0,"averageEthValue":0,"events":0,"usdValue":0,"averageUsdValue":0},"sales":{"ethValue":0.258,"averageEthValue":0.0516,"events":5,"usdValue":1052.2546085545,"averageUsdValue":210.4509217109}}}