{"_id":"0x72e4D76FbFff058C64621f5Dc960f09d24327743","_rev":null,"count":1,"rank":43,"overallRank":1440,"tokenIds":[9073],"latestTransactionInitiatorId":"0x72d4aee8faf9b9db5395327e8a02f21b0adf067ce9d92f61088c1a3b6e494ade","latestTransactionId":"0x72d4aee8faf9b9db5395327e8a02f21b0adf067ce9d92f61088c1a3b6e494ade","ensName":null,"lastActive":"2021-12-31T01:41:54.000Z","lastUpdated":"2023-02-11T16:45:58.619Z","dateCreated":"2023-02-11T16:45:58.619Z","salesReport":{"buys":{"ethValue":0.059,"averageEthValue":0.059,"events":1,"usdValue":219.79927143474998,"averageUsdValue":219.79927143474998},"sales":{"ethValue":0,"averageEthValue":0,"events":0,"usdValue":0,"averageUsdValue":0}}}