{"_id":"0x78b665207f3Ba6178A41E800f4173D1776779Abf","_rev":null,"count":1,"rank":47,"overallRank":1469,"tokenIds":[4701],"latestTransactionInitiatorId":"0x7337895b493b0d508b395db9dbe4d5ed0b24323721ff2d70a77f848b5d1b1f66","latestTransactionId":"0x7337895b493b0d508b395db9dbe4d5ed0b24323721ff2d70a77f848b5d1b1f66","ensName":null,"lastActive":"2021-12-27T17:03:56.000Z","lastUpdated":"2023-02-11T16:40:02.147Z","dateCreated":"2023-02-11T16:40:02.147Z","salesReport":{"buys":{"ethValue":0.125,"averageEthValue":0.125,"events":1,"usdValue":511.48125,"averageUsdValue":511.48125},"sales":{"ethValue":0,"averageEthValue":0,"events":0,"usdValue":0,"averageUsdValue":0}}}