{"_id":"0x7C0056773dFf23546e9071020009333eD427F21F","_rev":null,"count":0,"rank":41,"overallRank":4015,"tokenIds":[],"latestTransactionInitiatorId":"0xcc2098fe67e9ef4ea6be7c2dd2f7b1e9a89f8eade0348876f36849795c19cd49","latestTransactionId":"0x1fd40e5501953c1327977eb8bf361b2c5493b4fee7cc948b12b23f0168168314","ensName":null,"lastActive":"2021-12-30T14:11:18.000Z","lastUpdated":"2023-02-11T16:49:43.189Z","dateCreated":"2023-02-11T16:42:24.467Z","salesReport":{"buys":{"ethValue":0.095,"averageEthValue":0.095,"events":1,"usdValue":359.31755,"averageUsdValue":359.31755},"sales":{"ethValue":0.07,"averageEthValue":0.07,"events":1,"usdValue":223.81310000000002,"averageUsdValue":223.81310000000002}}}