{"_id":"0xB5fdFbbdDC872D08D0203Cd6D69d5cE67Eb4c761","_rev":null,"count":5,"rank":37,"overallRank":309,"tokenIds":[6946,6947,6948,6949,6950],"latestTransactionInitiatorId":"0xa0b3c2c65152e57a2b9addd0ab1cc96b8294becbee07c35e11e0a0d5682b87eb","latestTransactionId":"0xa0b3c2c65152e57a2b9addd0ab1cc96b8294becbee07c35e11e0a0d5682b87eb","ensName":"theskintrichkid.eth","lastActive":"2021-12-27T12:05:28.000Z","lastUpdated":"2023-02-11T16:37:56.202Z","dateCreated":"2023-02-11T16:34:25.427Z","salesReport":{"buys":{"ethValue":0,"averageEthValue":0,"events":0,"usdValue":0,"averageUsdValue":0},"sales":{"ethValue":0,"averageEthValue":0,"events":0,"usdValue":0,"averageUsdValue":0}}}