{"_id":"0xB81b7dF968d1C636Ba273E7268580546a881C254","_rev":null,"count":1,"rank":44,"overallRank":1449,"tokenIds":[2380],"latestTransactionInitiatorId":"0x756096df314f54e2bf990d8631478324d7b5a4facefab9718abd9b972f926e53","latestTransactionId":"0x756096df314f54e2bf990d8631478324d7b5a4facefab9718abd9b972f926e53","ensName":null,"lastActive":"2021-12-28T11:41:59.000Z","lastUpdated":"2023-02-11T16:42:23.902Z","dateCreated":"2023-02-11T16:42:23.902Z","salesReport":{"buys":{"ethValue":0.08,"averageEthValue":0.08,"events":1,"usdValue":312.47360000000003,"averageUsdValue":312.47360000000003},"sales":{"ethValue":0,"averageEthValue":0,"events":0,"usdValue":0,"averageUsdValue":0}}}