{"_id":"0xc44505d1111EC42279AedE122A77CBa17359438d","_rev":null,"count":5,"rank":46,"overallRank":387,"tokenIds":[8243,8244,8245,8246,8247],"latestTransactionInitiatorId":"0xda13d74eb7f37f586fb00216746d4e03dbb60adf13dd8d78bc2a473d2fb4adfa","latestTransactionId":"0xda13d74eb7f37f586fb00216746d4e03dbb60adf13dd8d78bc2a473d2fb4adfa","ensName":"poupa.eth","lastActive":"2021-12-26T21:56:35.000Z","lastUpdated":"2023-02-11T16:34:25.477Z","dateCreated":"2023-02-11T16:34:25.477Z","salesReport":{"buys":{"ethValue":0,"averageEthValue":0,"events":0,"usdValue":0,"averageUsdValue":0},"sales":{"ethValue":0,"averageEthValue":0,"events":0,"usdValue":0,"averageUsdValue":0}}}