{"_id":"0xcE256C77840Ed53E2EAb0Cfae41b2445AaB8E98f","_rev":null,"count":2,"rank":47,"overallRank":872,"tokenIds":[8374,8374],"latestTransactionInitiatorId":"0x619dfd6ce856ccdfb3cd091fd63fa00de042e6e8c076cf7522724f9e4940ccd5","latestTransactionId":"0xbb905d6b2561be79b17d903a83f992c04c7ef6f6777354bcad71b2132b54c032","ensName":null,"lastActive":"2021-12-26T22:04:49.000Z","lastUpdated":"2023-02-11T16:35:18.270Z","dateCreated":"2023-02-11T16:34:25.482Z","salesReport":{"buys":{"ethValue":0,"averageEthValue":0,"events":0,"usdValue":0,"averageUsdValue":0},"sales":{"ethValue":0.034,"averageEthValue":0.017,"events":2,"usdValue":139.33607999999998,"averageUsdValue":69.66803999999999}}}