{"_id":"0xDBc11CfE0992fFEa3B1754aa29B32Fde34785ea8","_rev":null,"count":2,"rank":43,"overallRank":731,"tokenIds":[2225,2963],"latestTransactionInitiatorId":"0x4e3893483528548fad68adff4de9630670734a762baaf7ed9dcb16248e0ece91","latestTransactionId":"0x4e3893483528548fad68adff4de9630670734a762baaf7ed9dcb16248e0ece91","ensName":null,"lastActive":"2021-12-28T05:12:30.000Z","lastUpdated":"2023-02-11T16:42:23.618Z","dateCreated":"2023-02-11T16:42:23.618Z","salesReport":{"buys":{"ethValue":0.399,"averageEthValue":0.1995,"events":2,"usdValue":1568.8022057905,"averageUsdValue":784.40110289525},"sales":{"ethValue":0,"averageEthValue":0,"events":0,"usdValue":0,"averageUsdValue":0}}}