{"_id":"0xDDB95D7eCb0E031a282D5D688fb2F4bE0C1B50bF","_rev":null,"count":2,"rank":40,"overallRank":845,"tokenIds":[7478,7480],"latestTransactionInitiatorId":"0xae1ab6cfa2b97101ac6dff2e5d92da8cf0e75e0753e762915e61ef024d76ff9e","latestTransactionId":"0xf13f912dd2cd0f697c6e3f58fe054ca06b6d8b8a16375f7579051d5699184193","ensName":null,"lastActive":"2021-12-26T22:10:55.000Z","lastUpdated":"2023-02-11T16:37:56.139Z","dateCreated":"2023-02-11T16:34:25.449Z","salesReport":{"buys":{"ethValue":0,"averageEthValue":0,"events":0,"usdValue":0,"averageUsdValue":0},"sales":{"ethValue":0.175,"averageEthValue":0.05833333333333333,"events":3,"usdValue":711.08340045765,"averageUsdValue":237.02780015255}}}