{"_id":"0xEa87cd8dEb1Cf95e4e44d6cACE7B80F48b4ccF75","_rev":null,"count":3,"rank":38,"overallRank":393,"tokenIds":[1360,1522,1719],"latestTransactionInitiatorId":"0x7e39c17e5e50b9e9ed91088053c432787eae4733519c5bb8d95258e6c9c26389","latestTransactionId":"0x7e39c17e5e50b9e9ed91088053c432787eae4733519c5bb8d95258e6c9c26389","ensName":null,"lastActive":"2022-02-10T10:58:21.000Z","lastUpdated":"2023-02-11T16:49:43.261Z","dateCreated":"2023-02-11T16:49:43.261Z","salesReport":{"buys":{"ethValue":0.105,"averageEthValue":0.034999999999999996,"events":3,"usdValue":313.9292871553,"averageUsdValue":104.64309571843334},"sales":{"ethValue":0,"averageEthValue":0,"events":0,"usdValue":0,"averageUsdValue":0}}}