{"_id":"0xebE7E229783dC3fadfa4dD8b2e3C42e5E9180337","_rev":null,"count":2,"rank":46,"overallRank":777,"tokenIds":[7172,8404],"latestTransactionInitiatorId":"0xc6673d267854479a89339a6000b9017fbe399b6d0db620118a540bef10454eef","latestTransactionId":"0xf3e92d00d85ecd2e495fdd3b89a6f4d4cddb6f427b088ea71b5d10d97c7fb122","ensName":"realrains.eth","lastActive":"2021-12-27T00:00:08.000Z","lastUpdated":"2023-02-11T16:40:02.070Z","dateCreated":"2023-02-11T16:36:23.971Z","salesReport":{"buys":{"ethValue":0.061,"averageEthValue":0.01525,"events":4,"usdValue":249.25774764352002,"averageUsdValue":62.314436910880005},"sales":{"ethValue":0.2138,"averageEthValue":0.1069,"events":2,"usdValue":873.698941588147,"averageUsdValue":436.8494707940735}}}