{"_id":"0xF953A6C8ACF7719bfcbefEc8De498f7d79F056D8","_rev":null,"count":8,"rank":43,"overallRank":291,"tokenIds":[4776,4777,4778,4779,4780,4781,4782,4783],"latestTransactionInitiatorId":"0x010b3bb5b1587c9347ab760b46a7f1463208b7442240ffc6e023c5e5668966f5","latestTransactionId":"0x010b3bb5b1587c9347ab760b46a7f1463208b7442240ffc6e023c5e5668966f5","ensName":"0xfineart.eth","lastActive":"2021-12-26T21:42:11.000Z","lastUpdated":"2023-02-11T16:34:25.321Z","dateCreated":"2023-02-11T16:34:25.321Z","salesReport":{"buys":{"ethValue":0,"averageEthValue":0,"events":0,"usdValue":0,"averageUsdValue":0},"sales":{"ethValue":0,"averageEthValue":0,"events":0,"usdValue":0,"averageUsdValue":0}}}