{"_id":"0xFB537262f8d7cB5Aa9bCcB2b7d0201B6048AefA3","_rev":null,"count":0,"rank":49,"overallRank":3909,"tokenIds":[],"latestTransactionInitiatorId":"0x4d6828df901d2198632a2d77ad61a0ec18ed7ca9bd03076e5299480ed65eea72","latestTransactionId":"0xab4ffd2185f4eae90f874f12a2c610f95c2ba78d573d69e8525edfe80fbcc54f","ensName":null,"lastActive":"2021-12-28T14:09:32.000Z","lastUpdated":"2023-02-11T16:54:01.573Z","dateCreated":"2023-02-11T16:42:23.444Z","salesReport":{"buys":{"ethValue":0.147,"averageEthValue":0.147,"events":1,"usdValue":583.06829639142,"averageUsdValue":583.06829639142},"sales":{"ethValue":0.02,"averageEthValue":0.02,"events":1,"usdValue":39.051525781,"averageUsdValue":39.051525781}}}