{"_id":"0xfB84B0ff856E01e7a7bC0c97e9183F22A03B2580","_rev":null,"count":1,"rank":40,"overallRank":1341,"tokenIds":[9829],"latestTransactionInitiatorId":"0x723bdc66c34eb97e1a8c0981ea540f0edabf1f4e2b24a14961d893edbb2297ac","latestTransactionId":"0x723bdc66c34eb97e1a8c0981ea540f0edabf1f4e2b24a14961d893edbb2297ac","ensName":null,"lastActive":"2022-01-17T02:37:34.000Z","lastUpdated":"2023-02-11T16:49:43.362Z","dateCreated":"2023-02-11T16:49:43.362Z","salesReport":{"buys":{"ethValue":0.04,"averageEthValue":0.04,"events":1,"usdValue":132.9872,"averageUsdValue":132.9872},"sales":{"ethValue":0,"averageEthValue":0,"events":0,"usdValue":0,"averageUsdValue":0}}}