{"_id":"0xFd96bC289b6E74A8B496d09b4C3c8fD3A76ee2e4","_rev":null,"count":1,"rank":48,"overallRank":1236,"tokenIds":[7622],"latestTransactionInitiatorId":null,"latestTransactionId":"0x6cd8e250837f55e8ee097c735e454aafc3def05718c0b573f4efb72a1d954e36","ensName":null,"lastActive":null,"lastUpdated":"2023-02-11T16:54:01.618Z","dateCreated":"2023-02-11T16:54:01.618Z","salesReport":{"buys":{"ethValue":0,"averageEthValue":0,"events":0,"usdValue":0,"averageUsdValue":0},"sales":{"ethValue":0,"averageEthValue":0,"events":0,"usdValue":0,"averageUsdValue":0}}}