{"_id":"0xfe13Dd552833Fb3498d0645274d847E06a5Ab086","_rev":null,"count":1,"rank":40,"overallRank":1341,"tokenIds":[3516],"latestTransactionInitiatorId":"0x0834ea5a1c864f1c45564137ffcef45f7b0c466dca1de96f13e77683d4dfce4f","latestTransactionId":"0x0834ea5a1c864f1c45564137ffcef45f7b0c466dca1de96f13e77683d4dfce4f","ensName":null,"lastActive":"2022-01-28T03:00:10.000Z","lastUpdated":"2023-02-11T16:49:43.447Z","dateCreated":"2023-02-11T16:45:59.078Z","salesReport":{"buys":{"ethValue":0.11,"averageEthValue":0.11,"events":1,"usdValue":413.4844315767,"averageUsdValue":413.4844315767},"sales":{"ethValue":0,"averageEthValue":0,"events":0,"usdValue":0,"averageUsdValue":0}}}