{"_id":"0x93601eD6415F675FCD9beA0d86DDb1b167F1a578","tokenIds":[18,4697],"count":2,"lastActive":"2022-01-02T09:50:04.000Z","transactionCount":2,"ensName":"survived2022bearmarket.eth","lastUpdated":"2023-03-29T16:44:41.284Z","dateCreated":"2023-03-29T16:44:41.284Z","rank":50,"overallRank":667,"salesReport":{"buys":{"ethValue":0.21000000000000002,"averageEthValue":0.10500000000000001,"events":2,"usdValue":786.6453,"averageUsdValue":393.32265},"sales":{"ethValue":0,"averageEthValue":0,"events":0,"usdValue":0,"averageUsdValue":0}},"totalTransactionPages":1}