{"_id":"0x1F370f6c38a4888DA33bB1D79e0FC01b3a51eFfb","tokenIds":[5555],"count":1,"lastActive":"2021-12-29T17:34:56.000Z","transactionCount":1,"ensName":"drhhhhhh.eth","lastUpdated":"2023-03-29T16:44:19.169Z","dateCreated":"2023-03-29T16:43:59.012Z","rank":51,"overallRank":1336,"salesReport":{"buys":{"ethValue":0.3,"averageEthValue":0.3,"events":1,"usdValue":1225.3666817189999,"averageUsdValue":1225.3666817189999},"sales":{"ethValue":0,"averageEthValue":0,"events":0,"usdValue":0,"averageUsdValue":0}},"totalTransactionPages":1}