{"_id":"0x007F9D679769Aa139B969eB524bB2d902E2C0fee","tokenIds":[],"count":0,"lastActive":"2021-12-27T14:42:16.000Z","transactionCount":2,"ensName":null,"lastUpdated":"2023-03-29T16:43:58.789Z","dateCreated":"2023-03-29T16:43:58.789Z","rank":52,"overallRank":3974,"salesReport":{"buys":{"ethValue":0.011,"averageEthValue":0.011,"events":1,"usdValue":45.04843087712,"averageUsdValue":45.04843087712},"sales":{"ethValue":0.097,"averageEthValue":0.097,"events":1,"usdValue":397.24525409824,"averageUsdValue":397.24525409824}},"totalTransactionPages":1}