{"_id":"0x0453666Dd9E1a17F8B38cEA6d2B9189546263572","tokenIds":[2373,2558,3170,4031,5560,6213,6373,6690,8209],"count":9,"lastActive":"2022-11-22T18:15:35.000Z","transactionCount":4,"ensName":null,"lastUpdated":"2023-03-29T16:45:22.035Z","dateCreated":"2023-03-29T16:45:22.035Z","rank":43,"overallRank":104,"salesReport":{"buys":{"ethValue":0.010299999999999998,"averageEthValue":0.0017166666666666665,"events":6,"usdValue":17.258277999999994,"averageUsdValue":2.8763796666666654},"sales":{"ethValue":0,"averageEthValue":0,"events":0,"usdValue":0,"averageUsdValue":0}},"totalTransactionPages":1}