{"_id":"0x11Ca33b58aBBaA2A068aAA8DaDd8f46B93fC82e3","tokenIds":[],"count":0,"lastActive":"2021-12-27T06:52:07.000Z","transactionCount":2,"ensName":null,"lastUpdated":"2023-03-29T16:44:19.018Z","dateCreated":"2023-03-29T16:43:38.261Z","rank":52,"overallRank":3974,"salesReport":{"buys":{"ethValue":0.075,"averageEthValue":0.075,"events":1,"usdValue":305.37719230799996,"averageUsdValue":305.37719230799996},"sales":{"ethValue":0.14,"averageEthValue":0.14,"events":1,"usdValue":533.3430598272,"averageUsdValue":533.3430598272}},"totalTransactionPages":1}